cellvit/__init__.py
cellvit/check_system.py
cellvit/detect_cells.py
cellvit/ray_logger_test.py
cellvit/config/__init__.py
cellvit/config/config.py
cellvit/config/templates.py
cellvit/data/dataclass/__init__.py
cellvit/data/dataclass/cell_graph.py
cellvit/data/dataclass/wsi.py
cellvit/data/dataclass/wsi_meta.py
cellvit/inference/__init__.py
cellvit/inference/cli.py
cellvit/inference/inference.py
cellvit/inference/overlap_cell_cleaner.py
cellvit/inference/postprocessing_cupy.py
cellvit/inference/postprocessing_numpy.py
cellvit/models/__init__.py
cellvit/models/base/__init__.py
cellvit/models/base/vision_transformer.py
cellvit/models/cell_segmentation/__init__.py
cellvit/models/cell_segmentation/backbones.py
cellvit/models/cell_segmentation/cellvit.py
cellvit/models/cell_segmentation/cellvit_256.py
cellvit/models/cell_segmentation/cellvit_sam.py
cellvit/models/cell_segmentation/postprocessing.py
cellvit/models/classifier/__init__.py
cellvit/models/classifier/linear_classifier.py
cellvit/models/utils/__init__.py
cellvit/models/utils/blocks.py
cellvit/models/utils/download_models.py
cellvit/models/utils/sam_utils.py
cellvit/utils/__init__.py
cellvit/utils/cache_models.py
cellvit/utils/cache_test_database.py
cellvit/utils/check_cupy.py
cellvit/utils/check_module.py
cellvit/utils/check_ray.py
cellvit/utils/clean_classifier.py
cellvit/utils/download.py
cellvit/utils/logger.py
cellvit/utils/ressource_manager.py
cellvit/utils/tools.py
cellvit/utils/tools_cp.py
cellvit-1.0.9.dist-info/licenses/LICENSE
docs/README-PyPI.md
docs/source/conf.py
cellvit-1.0.9.dist-info/METADATA
cellvit-1.0.9.dist-info/WHEEL
cellvit-1.0.9.dist-info/entry_points.txt
cellvit-1.0.9.dist-info/top_level.txt
cellvit-1.0.9.dist-info/RECORD
