Metadata-Version: 2.4
Name: cellvit
Version: 1.0.9
Summary: CellViT Inference Pipeline for Whole Slide Images (WSI) in Memory
Author-email: Fabian Hörst <fabian.hoerst@uk-essen.de>
License: Apache 2.0 with common clause, see LICENSE
Project-URL: Homepage, https://github.com/TIO-IKIM/CellViT-Inference
Project-URL: Documentation, https://tio-ikim.github.io/CellViT-Inference/
Project-URL: License, https://github.com/TIO-IKIM/CellViT-Inference/blob/main/LICENSE
Classifier: Development Status :: 4 - Beta
Classifier: Intended Audience :: Education
Classifier: Topic :: Scientific/Engineering :: Artificial Intelligence
Classifier: Programming Language :: Python :: 3
Classifier: Operating System :: MacOS :: MacOS X
Classifier: Operating System :: Microsoft :: Windows
Classifier: Operating System :: POSIX :: Other
Requires-Python: >=3.9
License-File: LICENSE
Requires-Dist: colorama
Requires-Dist: colour
Requires-Dist: einops>=0.6.1
Requires-Dist: geojson>=2.0.0
Requires-Dist: natsort
Requires-Dist: numba>=0.58.0
Requires-Dist: numpy<2.0.0
Requires-Dist: opencv-python-headless==4.7.0.72
Requires-Dist: opt-einsum>=3.3.0
Requires-Dist: pandas
Requires-Dist: pathopatch>=1.0.9
Requires-Dist: pydantic<2.0,>=1.10.16
Requires-Dist: pydicom==2.4.4
Requires-Dist: ray[default]>=2.9.3
Requires-Dist: scikit-image<0.27,>=0.19.3
Requires-Dist: scipy>=1.8.0
Requires-Dist: Shapely<=2.0.5,>=1.8.5.post1
Requires-Dist: ujson==5.8.0
Requires-Dist: python-snappy
Requires-Dist: tqdm
Requires-Dist: psutil
Requires-Dist: pyaml
Dynamic: license-file
